opscan/__init__.py
opscan/__main__.py
opscan/scanner.py
opscan-1.1.0.dist-info/licenses/LICENSE
opscan-1.1.0.dist-info/METADATA
opscan-1.1.0.dist-info/WHEEL
opscan-1.1.0.dist-info/entry_points.txt
opscan-1.1.0.dist-info/top_level.txt
opscan-1.1.0.dist-info/RECORD
