Metadata-Version: 2.4
Name: opscan
Version: 1.1.0
Summary: A fast and simple Python-based open port scanner.
Home-page: https://github.com/mr-bala-kavi/pypackage-opscan
Author: Mr.Balakavi
Author-email: balakavi64@gmail.com
License: MIT
Classifier: Programming Language :: Python :: 3
Classifier: License :: OSI Approved :: MIT License
Classifier: Operating System :: OS Independent
Classifier: Topic :: Security
Classifier: Topic :: Utilities
Classifier: Intended Audience :: Developers
Requires-Python: >=3.6
License-File: LICENSE
Dynamic: author
Dynamic: author-email
Dynamic: classifier
Dynamic: home-page
Dynamic: license
Dynamic: license-file
Dynamic: requires-python
Dynamic: summary
